source/debouncing.sv
module debouncing (
input logic clk, rst,
input logic en,
input logic [3:0] row, 
output logic [3:0] buttonMux
);

logic [3:0] newRow, newRow_n, oldRow, oldRow_n, oldestRow, oldestRow_n;
always_ff @(posedge clk, posedge rst) begin
    if (rst) begin
        newRow <= 4'b0;
    end else begin
        newRow <= newRow_n;
    end
end

// If needed, we may want to base this edge detector on counters to support debouncing 
always_comb begin 
    if (en) begin 
        newRow_n = row;
    end else begin
        newRow_n = 4'b0; // If we are not interested in this column, we should output active low
    end
end

always_ff @(posedge clk, posedge rst) begin
    if (rst) begin
        oldRow <= 4'b0;
    end else begin
        oldRow <= oldRow_n;
    end
end

always_comb begin 
    if (en) begin 
        oldRow_n = newRow;
    end else begin
        newRow    <= 4'b0;
        oldRow    <= 4'b0;
        oldestRow <= 4'b0;
    end
end

// If the recent data is high and the less recent data is low, we must have a positive edge
assign buttonMux =(~oldestRow & oldRow);

endmodule

testbench/debouncing_tb.sv
`timescale 1ns/1ps
`default_nettype none

module debouncing_tb();

    // DUT Inputs
    logic clk;
    logic rst;
    logic en;
    logic [3:0] row;

    // DUT Outputs
    logic [3:0] buttonMux;

    // Clock generation: 10ns period (100 MHz)
    initial clk = 0;
    always #5 clk = ~clk; //flip clock every 1/2 period

    // DUT instantiation
    debouncing DUT(
        .clk(clk),
        .rst(rst),
        .en(en),
        .row(row),
        .buttonMux(buttonMux)
    );

    // Simple printing utility
    task show(input string msg);
        $display("[%0t] %s | en=%b row=%b -> buttonMux=%b",
                 $time, msg, en, row, buttonMux);
    endtask


    initial begin
        $dumpvars(0, debouncing_tb);
        $dumpfile("debouncing_tb.vcd");
        // INITIAL RESET
        rst = 1;
        en  = 0;
        row = 4'b0000;
        repeat(3) @(posedge clk);
        rst = 0;

        show("After reset");

        // Flush pipeline
        @(negedge clk); row = 4'b0000;
        @(negedge clk); row = 4'b0000;
        @(negedge clk); row = 4'b0000;
        @(negedge clk); row = 4'b0000;
        @(negedge clk); row = 4'b0000;

        // TEST 1: No enable, output must be zero
        repeat(5) begin
            @(negedge clk);
            row = $urandom % 16;
            show("EN=0: Output must remain zero"); //outputs should be 0 due to enable being low active
        end

        @(negedge clk); row = 4'b0000;
        @(negedge clk); row = 4'b0000;
        @(negedge clk); row = 4'b0000;
        @(negedge clk); row = 4'b0000;
        @(negedge clk); row = 4'b0000;


        // TEST 2: Rising edge on row[0]
        $display("\n TEST 2: Rising edge on row[0] -- ");
        @(negedge clk); en = 1;

        //flush pipeline (pipeline is 3 stages deep)
        @(negedge clk); row = 4'b0000; show("Pipeline flush 1");
        @(negedge clk); row = 4'b0000; show("Pipeline flush 2"); 

        //make sure to change on negedge of the clock to avoid race conditions
        @(negedge clk); row = 4'b0000; show("Start: no key");
        @(negedge clk); row = 4'b0001; show("Row0 rises - expect buttonMux = 0001");
        @(negedge clk); row = 4'b0001; show("Hold → expect buttonMux = 0000");


        // TEST 3: Rising edge on row[3]
        $display("\n TEST 3: Rising edge on row[3] -- ");

        @(negedge clk); row = 4'b0000; show("Reset rows");

        //flush pipeline
        @(negedge clk); row = 4'b0000; show("Pipeline flush 3");
        @(negedge clk); row = 4'b0000; show("Pipeline flush 4");

        @(negedge clk); row = 4'b1000; show("Row3 rises - expect buttonMux = 1000");
        @(negedge clk); row = 4'b1000; show("Hold → expect buttonMux = 0000");


        // TEST 4: Simulate button bounce
        $display("\n TEST 4: Bounce simulation -- ");
        @(negedge clk); row = 4'b0000; show("Idle");
        @(negedge clk); row = 4'b0100; show("Bounce high");
        @(negedge clk); row = 4'b0000; show("Bounce low");
        @(negedge clk); row = 4'b0100; show("Final high - expect buttonMux = 0100");


        // TEST 5: Disable during activity
        $display("\n TEST 5: Disable during row change -- ");

        @(negedge clk); en = 0; row = 4'b1111; show("EN=0: Output forced to 0");
        @(negedge clk); row = 4'b0001; show("Still EN=0: Output forced to 0");


        // End simulation
        $display("\nSimulation complete.");
        $finish;
    end

endmodule

dump.vcd
$date
	Tue Dec  2 20:29:12 2025
$end
$version
	Icarus Verilog
$end
$timescale
	1ps
$end
$scope module debouncing_tb $end
$var wire 4 ! buttonMux [3:0] $end
$var reg 1 " clk $end
$var reg 1 # en $end
$var reg 4 $ row [3:0] $end
$var reg 1 % rst $end
$scope module DUT $end
$var wire 4 & buttonMux [3:0] $end
$var wire 1 " clk $end
$var wire 1 # en $end
$var wire 4 ' row [3:0] $end
$var wire 1 % rst $end
$var reg 4 ( newRow [3:0] $end
$var reg 4 ) newRow_n [3:0] $end
$var reg 4 * oldRow [3:0] $end
$var reg 4 + oldRow_n [3:0] $end
$var reg 4 , oldestRow [3:0] $end
$var reg 4 - oldestRow_n [3:0] $end
$upscope $end
$scope task show $end
$upscope $end
$upscope $end
$enddefinitions $end
#0
$dumpvars
b0 -
b0 ,
b0 +
b0 *
b0 )
b0 (
b0 '
b0 &
1%
b0 $
0#
0"
b0 !
$end
#5000
1"
#10000
0"
#15000
1"
#20000
0"
#25000
0%
1"
#30000
0"
#35000
1"
#40000
0"
#45000
1"
#50000
0"
#55000
1"
#60000
0"
#65000
1"
#70000
0"
#75000
1"
#80000
b100 $
b100 '
0"
#85000
1"
#90000
b1 $
b1 '
0"
#95000
1"
#100000
b1001 $
b1001 '
0"
#105000
1"
#110000
b11 $
b11 '
0"
#115000
1"
#120000
b1101 $
b1101 '
0"
#125000
1"
#130000
b0 $
b0 '
0"
#135000
1"
#140000
0"
#145000
1"
#150000
0"
#155000
1"
#160000
0"
#165000
1"
#170000
0"
#175000
1"
#180000
1#
0"
#185000
1"
#190000
0"
#195000
1"
#200000
0"
#205000
1"
#210000
0"
#215000
1"
#220000
b1 )
b1 $
b1 '
0"
#225000
b1 +
b1 (
1"
#230000
0"
#235000
b1 -
b1 !
b1 &
b1 *
1"
#240000
b0 )
b0 $
b0 '
0"
#245000
b0 !
b0 &
b0 +
b1 ,
b0 (
1"
#250000
0"
#255000
b0 -
b0 *
1"
#260000
0"
#265000
b0 ,
1"
#270000
b1000 )
b1000 $
b1000 '
0"
#275000
b1000 +
b1000 (
1"
#280000
0"
#285000
b1000 -
b1000 !
b1000 &
b1000 *
1"
#290000
b0 )
b0 $
b0 '
0"
#295000
b0 !
b0 &
b0 +
b0 (
b1000 ,
1"
#300000
b100 )
b100 $
b100 '
0"
#305000
b0 -
b100 +
b0 *
b100 (
1"
#310000
b0 )
b0 $
b0 '
0"
#315000
b0 +
b100 -
b100 !
b100 &
b0 (
b100 *
b0 ,
1"
#320000
b100 )
b100 $
b100 '
0"
#325000
b0 -
b0 !
b0 &
b100 +
b100 ,
b0 *
b100 (
1"
#330000
b0 +
b0 )
b1111 $
b1111 '
0#
0"
#335000
b0 (
b0 ,
1"
#340000
b1 $
b1 '
0"
